persistence_client/__init__.py
persistence_client/client.py
persistence_client/schemas.py
persistence_client-0.1.8.dist-info/METADATA
persistence_client-0.1.8.dist-info/WHEEL
persistence_client-0.1.8.dist-info/entry_points.txt
persistence_client-0.1.8.dist-info/top_level.txt
persistence_client-0.1.8.dist-info/RECORD
